qubecrawl/__init__.py
qubecrawl/qubecrawl.py
qubecrawl-0.1.2.dist-info/LICENSE
qubecrawl-0.1.2.dist-info/METADATA
qubecrawl-0.1.2.dist-info/WHEEL
qubecrawl-0.1.2.dist-info/top_level.txt
qubecrawl-0.1.2.dist-info/RECORD
