Metadata-Version: 2.1
Name: qubecrawl
Version: 0.1.2
Summary: qubecrawl is a lightweight and LLLM friendly Webscraper that extracts HTML content and converts it into clean, readable Markdown to reduce token.
Home-page: https://github.com/adhishtanaka/qubecrawl
Author: Adhishtanaka Thiramithu Kulasooriya
Author-email: Adhishtanaka Thiramithu Kulasooriya <kulasoooriyaa@gmail.com>
Project-URL: Homepage, https://github.com/adhishtanaka/qubecrawl/
Project-URL: Issues, https://github.com/adhishtanaka/qubecrawl/issues
Classifier: Programming Language :: Python :: 3
Classifier: License :: OSI Approved :: MIT License
Classifier: Operating System :: OS Independent
Classifier: Intended Audience :: Developers
Classifier: Topic :: Software Development :: Libraries :: Python Modules
Requires-Python: >=3.8
License-File: LICENSE
Requires-Dist: beautifulsoup4
Requires-Dist: html2text
Requires-Dist: lxml
Requires-Dist: requests
Provides-Extra: dev
Requires-Dist: twine; extra == "dev"
